[{"prediction": "moped", "probability": 65.02519249916077, "prediction_translated": "Moped"}, {"prediction": "mountain_bike", "probability": 28.07711362838745, "prediction_translated": "Mountainbike"}, {"prediction": "motor_scooter", "probability": 2.771378681063652, "prediction_translated": "Motorroller"}, {"prediction": "bicycle-built-for-two", "probability": 1.8433371558785439, "prediction_translated": "Fahrrad-gebaut-f\u00fcr-zwei"}, {"prediction": "tricycle", "probability": 0.6797465495765209, "prediction_translated": "Dreirad"}]